kashima/__init__.py
kashima/mapper/__init__.py
kashima/mapper/api.py
kashima/mapper/base_map.py
kashima/mapper/blast_catalog.py
kashima/mapper/cache.py
kashima/mapper/config.py
kashima/mapper/event_map.py
kashima/mapper/gcmt_catalog.py
kashima/mapper/isc_bulletin_catalog.py
kashima/mapper/isc_catalog.py
kashima/mapper/usgs_catalog.py
kashima/mapper/utils.py
kashima/mapper/data/gcmt_catalog.csv
kashima/mapper/data/gem_active_faults.geojson
kashima/mapper/data/isc_catalog.csv
kashima/mapper/data/usgs_catalog.csv
kashima/mapper/layers/__init__.py
kashima/mapper/layers/_layer_base.py
kashima/mapper/layers/beachballs.py
kashima/mapper/layers/epicentral_circles.py
kashima/mapper/layers/event_markers.py
kashima/mapper/layers/faults.py
kashima/mapper/layers/heatmap.py
kashima/mapper/layers/site_marker.py
kashima/mapper/layers/stations.py
kashima-1.3.4.dist-info/METADATA
kashima-1.3.4.dist-info/WHEEL
kashima-1.3.4.dist-info/top_level.txt
kashima-1.3.4.dist-info/RECORD
