Metadata-Version: 2.4
Name: kashima
Version: 1.3.4
Summary: Machine Learning Tools for Geotechnical Earthquake Engineering.
Home-page: https://github.com/SRKConsulting/kashima
Author: Alejandro Verri Kozlowski
Author-email: averri@fi.uba.ar
Classifier: Programming Language :: Python :: 3
Classifier: Operating System :: OS Independent
Requires-Python: >=3.8
Requires-Dist: pandas>=1.3.0
Requires-Dist: numpy>=1.20.0
Requires-Dist: folium>=0.12.0
Requires-Dist: geopandas>=0.10.0
Requires-Dist: pyproj>=3.0.0
Requires-Dist: requests>=2.25.0
Requires-Dist: branca>=0.4.0
Requires-Dist: geopy>=2.0.0
Requires-Dist: matplotlib>=3.3.0
Requires-Dist: obspy>=1.2.0
Requires-Dist: appdirs>=1.4.0
Requires-Dist: pyarrow>=10.0.0
Dynamic: author
Dynamic: author-email
Dynamic: classifier
Dynamic: description
Dynamic: description-content-type
Dynamic: home-page
Dynamic: requires-dist
Dynamic: requires-python
Dynamic: summary
